dockchangelog/__init__.py
dockchangelog/checker.py
dockchangelog/cli.py
dockchangelog/config.py
dockchangelog/formatter.py
dockchangelog/github_client.py
dockchangelog/mapper.py
dockchangelog/parser.py
dockchangelog/update_checker.py
dockchangelog-0.5.0.dist-info/licenses/LICENSE
dockchangelog-0.5.0.dist-info/METADATA
dockchangelog-0.5.0.dist-info/WHEEL
dockchangelog-0.5.0.dist-info/entry_points.txt
dockchangelog-0.5.0.dist-info/top_level.txt
dockchangelog-0.5.0.dist-info/RECORD
