Metadata-Version: 2.4
Name: dockchangelog
Version: 0.5.0
Summary: check docker updates with github release notes
Author-email: Sahib Khokhar <skhokhar2003@gmail.com>
License: MIT
Project-URL: Homepage, https://github.com/sahibkhokhar/dockchangelog
Project-URL: Repository, https://github.com/sahibkhokhar/dockchangelog
Project-URL: Issues, https://github.com/sahibkhokhar/dockchangelog/issues
Project-URL: Documentation, https://github.com/sahibkhokhar/dockchangelog#readme
Keywords: docker,compose,updates,changelog,release-notes,github
Classifier: Development Status :: 3 - Alpha
Classifier: Intended Audience :: Developers
Classifier: Intended Audience :: System Administrators
Classifier: License :: OSI Approved :: MIT License
Classifier: Programming Language :: Python :: 3
Classifier: Programming Language :: Python :: 3.8
Classifier: Programming Language :: Python :: 3.9
Classifier: Programming Language :: Python :: 3.10
Classifier: Programming Language :: Python :: 3.11
Classifier: Programming Language :: Python :: 3.12
Classifier: Topic :: System :: Systems Administration
Classifier: Topic :: Utilities
Requires-Python: >=3.8
License-File: LICENSE
Requires-Dist: typer>=0.9.0
Requires-Dist: rich>=13.0.0
Requires-Dist: httpx>=0.25.0
Requires-Dist: pydantic>=2.0.0
Requires-Dist: pyyaml>=6.0
Provides-Extra: dev
Requires-Dist: pytest>=7.0.0; extra == "dev"
Requires-Dist: pytest-asyncio>=0.21.0; extra == "dev"
Requires-Dist: black>=23.0.0; extra == "dev"
Requires-Dist: ruff>=0.1.0; extra == "dev"
Dynamic: license-file
